driizzyy_compiler/__init__.py
driizzyy_compiler/gui.py
driizzyy_compiler/main.py
mycompiler-0.1.0.dist-info/METADATA
mycompiler-0.1.0.dist-info/WHEEL
mycompiler-0.1.0.dist-info/entry_points.txt
mycompiler-0.1.0.dist-info/top_level.txt
mycompiler-0.1.0.dist-info/RECORD
