Metadata-Version: 2.4
Name: mycompiler
Version: 0.1.0
Summary: GUI-based Python EXE compiler using PyInstaller
Author: DriizzyyB
License: MIT
Classifier: Programming Language :: Python :: 3
Classifier: Operating System :: OS Independent
Requires-Python: >=3.7
